adcorr/__init__.py
adcorr/__main__.py
adcorr/_version.py
adcorr/cli.py
adcorr/corrections/__init__.py
adcorr/corrections/angular_efficiency.py
adcorr/corrections/background_subtraction.py
adcorr/corrections/dark_current.py
adcorr/corrections/deadtime.py
adcorr/corrections/displaced_volume.py
adcorr/corrections/flatfield.py
adcorr/corrections/frame_average.py
adcorr/corrections/frame_time.py
adcorr/corrections/masking.py
adcorr/corrections/polarization.py
adcorr/corrections/self_absorption.py
adcorr/corrections/solid_angle.py
adcorr/corrections/thickness.py
adcorr/corrections/transmission.py
adcorr/sequences/__init__.py
adcorr/sequences/pauw.py
adcorr/utils/__init__.py
adcorr/utils/geometry.py
adcorr/utils/typing.py
adcorr-0.2.1.dist-info/LICENSE
adcorr-0.2.1.dist-info/METADATA
adcorr-0.2.1.dist-info/WHEEL
adcorr-0.2.1.dist-info/entry_points.txt
adcorr-0.2.1.dist-info/top_level.txt
adcorr-0.2.1.dist-info/RECORD
